ordered_set.py
ordered_set_minghu6-3.1.0.dist-info/METADATA
ordered_set_minghu6-3.1.0.dist-info/WHEEL
ordered_set_minghu6-3.1.0.dist-info/top_level.txt
ordered_set_minghu6-3.1.0.dist-info/RECORD
