Metadata-Version: 2.1
Name: ordered-set-minghu6
Version: 3.1.0
Summary: A Fork from LuminosoInsight/ordered-set, according to Pull requests #22 .
Home-page: http://github.com/minghu6/ordered-set
License: MIT-LICENSE
Platform: any
Classifier: Development Status :: 5 - Production/Stable
Classifier: Intended Audience :: Developers
Classifier: License :: OSI Approved :: MIT License
Classifier: Programming Language :: Python :: 2
Classifier: Programming Language :: Python :: 3
Classifier: Programming Language :: Python :: Implementation :: CPython
Classifier: Programming Language :: Python :: Implementation :: PyPy
